README
setup.py
aliyun_python_sdk_oss.egg-info/PKG-INFO
aliyun_python_sdk_oss.egg-info/SOURCES.txt
aliyun_python_sdk_oss.egg-info/dependency_links.txt
aliyun_python_sdk_oss.egg-info/top_level.txt
oss/__init__.py
oss/oss_api.py
oss/oss_sample.py
oss/oss_util.py
oss/oss_xml_handler.py
oss/pkg_info.py