Metadata-Version: 1.0
Name: aliyun-python-sdk-oss
Version: 0.4.4.0
Summary: Command line tool for managing Aliyun Open Storage Service.
Home-page: http://oss.aliyun.com
Author: Aliyun OSS
Author-email: UNKNOWN
License: MIT License
Platform: UNKNOWN
